AUTHORS.rst
CHANGES.rst
MANIFEST.in
README.rst
TODO.rst
setup.cfg
setup.py
malleefowl/__init__.py
malleefowl/config.py
malleefowl/download.py
malleefowl/process.py
malleefowl/swiftcloud.py
malleefowl/utils.py
malleefowl/workflow.py
malleefowl/wpslogging.py
malleefowl.egg-info/PKG-INFO
malleefowl.egg-info/SOURCES.txt
malleefowl.egg-info/dependency_links.txt
malleefowl.egg-info/entry_points.txt
malleefowl.egg-info/not-zip-safe
malleefowl.egg-info/pbr.json
malleefowl.egg-info/requires.txt
malleefowl.egg-info/top_level.txt
malleefowl/esgf/__init__.py
malleefowl/esgf/logon.py
malleefowl/esgf/search.py
malleefowl/processes/__init__.py
malleefowl/processes/wps_download.py
malleefowl/processes/wps_esgflogon.py
malleefowl/processes/wps_esgsearch.py
malleefowl/processes/wps_swift.py
malleefowl/processes/wps_thredds.py
malleefowl/processes/wps_workflow.py
malleefowl/templates/simple_workflow.yaml
tests/__init__.py
tests/common.py
tests/test_download.py
tests/test_esgf_logon.py
tests/test_esgf_search.py
tests/test_utils.py
tests/test_wps_caps.py
tests/test_wps_download.py
tests/test_wps_esgsearch.py
tests/test_wps_thredds.py
tests/test_wps_workflow.py