Metadata-Version: 1.1
Name: malleefowl
Version: 0.3.11
Summary: Malleefowl simplifies the usage of WPS and has some supporting WPS processes.
Home-page: https://github.com/bird-house/malleefowl
Author: Birdhouse
Author-email: UNKNOWN
License: Apache License v2.0
Keywords: wps pywps python malleefowl netcdf esgf
Platform: UNKNOWN
Classifier: Development Status :: 3 - Alpha
Classifier: Intended Audience :: Science/Research
Classifier: Operating System :: MacOS :: MacOS X
Classifier: Operating System :: Microsoft :: Windows
Classifier: Operating System :: POSIX
Classifier: Programming Language :: Python
Classifier: Topic :: Scientific/Engineering :: Atmospheric Science
